{"version":1,"collections":[{"id":"f0757b6e-de6a-353b-7dc5-9e3d41c48f0c","name":"博客后台","timestamp":1589447202709,"requests":[{"collectionId":"f0757b6e-de6a-353b-7dc5-9e3d41c48f0c","id":"142ccebb-30e3-2234-e4db-8cbe8535c447","name":"register","description":"注册用户","url":"http://127.0.0.1:8001/admin/register","method":"POST","headers":"","data":[{"key":"user_name","value":"admin","type":"text"},{"key":"password","value":"admin","type":"text"},{"key":"status","value":"1","type":"text"},{"key":"avatar","value":"","type":"file"}],"dataMode":"params","timestamp":0,"responses":[],"version":2},{"collectionId":"f0757b6e-de6a-353b-7dc5-9e3d41c48f0c","id":"29371d0f-39e4-e58a-872b-f46a38821455","name":"查询用户角色","description":"","url":"http://127.0.0.1:8001/auth/userRoles","method":"POST","headers":"","data":[{"key":"userName","value":"admin","type":"text"}],"dataMode":"urlencoded","timestamp":0,"responses":[],"version":2},{"collectionId":"f0757b6e-de6a-353b-7dc5-9e3d41c48f0c","id":"455f9bbf-eafa-174f-7cc6-e941f8feedde","name":"添加角色","description":"","url":"http://127.0.0.1:8001/auth/addRoles","method":"POST","headers":"","data":[{"key":"roleName","value":"test","type":"text"},{"key":"allows","value":"[{\"resources\":[\"/admin/login\",\"/admin/register\"],\"permissions\":[\"get\",\"post\"]}]","type":"text"}],"dataMode":"urlencoded","timestamp":0,"responses":[],"version":2},{"collectionId":"f0757b6e-de6a-353b-7dc5-9e3d41c48f0c","id":"b1929205-6726-b9af-8fb6-7a2497cbc795","name":"给用户添加角色","description":"","url":"http://127.0.0.1:8001/auth/addUserRoles","method":"POST","headers":"","data":[{"key":"roleName","value":"test","type":"text"},{"key":"userName","value":"admin","type":"text"}],"dataMode":"urlencoded","timestamp":0,"responses":[],"version":2},{"collectionId":"f0757b6e-de6a-353b-7dc5-9e3d41c48f0c","id":"b855f392-c9aa-f4aa-2d78-6b30aed2f24b","name":"给用户删除角色","description":"","url":"http://127.0.0.1:8001/auth/removeUserRoles","method":"POST","headers":"","data":[{"key":"roleName","value":"test","type":"text"},{"key":"userName","value":"admin","type":"text"}],"dataMode":"urlencoded","timestamp":0,"responses":[],"version":2},{"collectionId":"f0757b6e-de6a-353b-7dc5-9e3d41c48f0c","id":"defe4a66-f657-dd13-e3de-9eb0a9978453","name":"删除角色","description":"","url":"http://127.0.0.1:8001/auth/removeRole","method":"POST","headers":"","data":[{"key":"roleName","value":"test","type":"text"}],"dataMode":"urlencoded","timestamp":0,"responses":[],"version":2}]}],"environments":[],"headerPresets":[],"globals":[]}